scrapy_pipeline_mongodb/__init__.py
scrapy_pipeline_mongodb/_version.py
scrapy_pipeline_mongodb/signals.py
scrapy_pipeline_mongodb/pipelines/__init__.py
scrapy_pipeline_mongodb/pipelines/mongodb_async.py
scrapy_pipeline_mongodb/settings/__init__.py
scrapy_pipeline_mongodb/settings/default_settings.py
scrapy_pipeline_mongodb/utils/__init__.py
scrapy_pipeline_mongodb/utils/get_mongodb_uri.py
scrapy_pipeline_mongodb/utils/process_item.py
scrapy_pipeline_mongodb-0.0.7.dist-info/DESCRIPTION.rst
scrapy_pipeline_mongodb-0.0.7.dist-info/METADATA
scrapy_pipeline_mongodb-0.0.7.dist-info/RECORD
scrapy_pipeline_mongodb-0.0.7.dist-info/WHEEL
scrapy_pipeline_mongodb-0.0.7.dist-info/metadata.json
scrapy_pipeline_mongodb-0.0.7.dist-info/top_level.txt
